{
  "project_info": {
    "project_number": "645509903869",
    "project_id": "onlinshopping-1927f",
    "storage_bucket": "onlinshopping-1927f.appspot.com"
  },
  "client": [
    {
      "client_info": {
        "mobilesdk_app_id": "1:645509903869:android:59fd4492a15414e004d594",
        "android_client_info": {
          "package_name": "com.example.online_shopping"
        }
      },
      "oauth_client": [
        {
          "client_id": "645509903869-d2hd17du5uob87uvemkpmdrnis549sgd.apps.googleusercontent.com",
          "client_type": 3
        }
      ],
      "api_key": [
        {
          "current_key": "AIzaSyBZzqF42I77s7VRs7QnpJEr9Fem2yY9gaI"
        }
      ],
      "services": {
        "appinvite_service": {
          "other_platform_oauth_client": [
            {
              "client_id": "645509903869-d2hd17du5uob87uvemkpmdrnis549sgd.apps.googleusercontent.com",
              "client_type": 3
            }
          ]
        }
      }
    }
  ],
  "configuration_version": "1"
}